{
"meta":{"test_sets":[],"test_metrics":[],"learn_metrics":[{"best_value":"Min","name":"MultiClass"}],"launch_mode":"Train","parameters":"","iteration_count":100,"learn_sets":["learn"],"name":"experiment"},
"iterations":[
{"learn":[1.02112209],"iteration":0,"passed_time":0.004463518269,"remaining_time":0.4418883086},
{"learn":[0.9562360493],"iteration":1,"passed_time":0.0084372601,"remaining_time":0.4134257449},
{"learn":[0.9020137091],"iteration":2,"passed_time":0.01269162096,"remaining_time":0.4103624109},
{"learn":[0.8619923136],"iteration":3,"passed_time":0.01643522044,"remaining_time":0.3944452904},
{"learn":[0.8259668769],"iteration":4,"passed_time":0.02037670521,"remaining_time":0.387157399},
{"learn":[0.7944370804],"iteration":5,"passed_time":0.02453807836,"remaining_time":0.3844298943},
{"learn":[0.7615767223],"iteration":6,"passed_time":0.02855316949,"remaining_time":0.3793492518},
{"learn":[0.7372815809],"iteration":7,"passed_time":0.03216313657,"remaining_time":0.3698760706},
{"learn":[0.7119368527],"iteration":8,"passed_time":0.0359600846,"remaining_time":0.3635964109},
{"learn":[0.6924062536],"iteration":9,"passed_time":0.03991540288,"remaining_time":0.3592386259},
{"learn":[0.6745095521],"iteration":10,"passed_time":0.04362440044,"remaining_time":0.3529610581},
{"learn":[0.6587980292],"iteration":11,"passed_time":0.04728912604,"remaining_time":0.3467869243},
{"learn":[0.6454612354],"iteration":12,"passed_time":0.0508493222,"remaining_time":0.3402993101},
{"learn":[0.6317255056],"iteration":13,"passed_time":0.05494694236,"remaining_time":0.3375312173},
{"learn":[0.6185673113],"iteration":14,"passed_time":0.05872189341,"remaining_time":0.332757396},
{"learn":[0.606301124],"iteration":15,"passed_time":0.0624072675,"remaining_time":0.3276381544},
{"learn":[0.5930540641],"iteration":16,"passed_time":0.06621336734,"remaining_time":0.3232770288},
{"learn":[0.5837917096],"iteration":17,"passed_time":0.07158523503,"remaining_time":0.3261105152},
{"learn":[0.5762055158],"iteration":18,"passed_time":0.07527147603,"remaining_time":0.3208941873},
{"learn":[0.5666884345],"iteration":19,"passed_time":0.07901820211,"remaining_time":0.3160728084},
{"learn":[0.5599752142],"iteration":20,"passed_time":0.08257506506,"remaining_time":0.3106395305},
{"learn":[0.554722838],"iteration":21,"passed_time":0.08627532631,"remaining_time":0.3058852478},
{"learn":[0.5467654035],"iteration":22,"passed_time":0.08985701037,"remaining_time":0.3008256434},
{"learn":[0.5394592268],"iteration":23,"passed_time":0.09361594422,"remaining_time":0.29645049},
{"learn":[0.5319216002],"iteration":24,"passed_time":0.09777337694,"remaining_time":0.2933201308},
{"learn":[0.5256109547],"iteration":25,"passed_time":0.1020238031,"remaining_time":0.2903754396},
{"learn":[0.5181198551],"iteration":26,"passed_time":0.1057769027,"remaining_time":0.2859894036},
{"learn":[0.5128140636],"iteration":27,"passed_time":0.1101435394,"remaining_time":0.2832262442},
{"learn":[0.5083021433],"iteration":28,"passed_time":0.1143854183,"remaining_time":0.2800470586},
{"learn":[0.5039511967],"iteration":29,"passed_time":0.1194363087,"remaining_time":0.2786847203},
{"learn":[0.4978424824],"iteration":30,"passed_time":0.1235304792,"remaining_time":0.2749549375},
{"learn":[0.4933692997],"iteration":31,"passed_time":0.1274448946,"remaining_time":0.270820401},
{"learn":[0.4883014718],"iteration":32,"passed_time":0.1339058078,"remaining_time":0.2718693673},
{"learn":[0.4848705542],"iteration":33,"passed_time":0.1379048213,"remaining_time":0.2676975944},
{"learn":[0.4796316768],"iteration":34,"passed_time":0.1507103985,"remaining_time":0.2798907401},
{"learn":[0.4762643555],"iteration":35,"passed_time":0.1571657757,"remaining_time":0.2794058234},
{"learn":[0.4734937641],"iteration":36,"passed_time":0.1624071685,"remaining_time":0.2765311248},
{"learn":[0.4700390599],"iteration":37,"passed_time":0.1681290752,"remaining_time":0.2743158596},
{"learn":[0.4677487388],"iteration":38,"passed_time":0.1730362251,"remaining_time":0.2706464034},
{"learn":[0.4621036194],"iteration":39,"passed_time":0.1779543775,"remaining_time":0.2669315663},
{"learn":[0.457026884],"iteration":40,"passed_time":0.1834829729,"remaining_time":0.2640364732},
{"learn":[0.4509249912],"iteration":41,"passed_time":0.1879886578,"remaining_time":0.2596033845},
{"learn":[0.4490588083],"iteration":42,"passed_time":0.1930076214,"remaining_time":0.2558473121},
{"learn":[0.4471424382],"iteration":43,"passed_time":0.1977470301,"remaining_time":0.2516780383},
{"learn":[0.4434195815],"iteration":44,"passed_time":0.2022170299,"remaining_time":0.2471541477},
{"learn":[0.43959909],"iteration":45,"passed_time":0.2064996902,"remaining_time":0.2424126798},
{"learn":[0.4359556938],"iteration":46,"passed_time":0.2106753601,"remaining_time":0.2375700869},
{"learn":[0.4342994027],"iteration":47,"passed_time":0.2146956531,"remaining_time":0.2325869575},
{"learn":[0.4313862705],"iteration":48,"passed_time":0.2181341267,"remaining_time":0.2270375605},
{"learn":[0.4276408129],"iteration":49,"passed_time":0.2219168781,"remaining_time":0.2219168781},
{"learn":[0.4258935702],"iteration":50,"passed_time":0.2255702536,"remaining_time":0.2167243613},
{"learn":[0.4225608094],"iteration":51,"passed_time":0.2294026388,"remaining_time":0.211756282},
{"learn":[0.4196951993],"iteration":52,"passed_time":0.2328769498,"remaining_time":0.2065135215},
{"learn":[0.4174262572],"iteration":53,"passed_time":0.2364308553,"remaining_time":0.2014040619},
{"learn":[0.4118929332],"iteration":54,"passed_time":0.2402280157,"remaining_time":0.1965501946},
{"learn":[0.4097780595],"iteration":55,"passed_time":0.2437775301,"remaining_time":0.191539488},
{"learn":[0.4081819167],"iteration":56,"passed_time":0.2472770487,"remaining_time":0.186542335},
{"learn":[0.4066819862],"iteration":57,"passed_time":0.2506584606,"remaining_time":0.1815112991},
{"learn":[0.4035394446],"iteration":58,"passed_time":0.2541882974,"remaining_time":0.1766393253},
{"learn":[0.4014762403],"iteration":59,"passed_time":0.2580047322,"remaining_time":0.1720031548},
{"learn":[0.3998458725],"iteration":60,"passed_time":0.2615976108,"remaining_time":0.1672509315},
{"learn":[0.3961654462],"iteration":61,"passed_time":0.2651051527,"remaining_time":0.1624838033},
{"learn":[0.3925484804],"iteration":62,"passed_time":0.2685638815,"remaining_time":0.1577279939},
{"learn":[0.3891652176],"iteration":63,"passed_time":0.2723269177,"remaining_time":0.1531838912},
{"learn":[0.3876094694],"iteration":64,"passed_time":0.2756749051,"remaining_time":0.1484403335},
{"learn":[0.3855650872],"iteration":65,"passed_time":0.2791960124,"remaining_time":0.1438282488},
{"learn":[0.3830730949],"iteration":66,"passed_time":0.2826938392,"remaining_time":0.1392372641},
{"learn":[0.3803931718],"iteration":67,"passed_time":0.2862095846,"remaining_time":0.1346868634},
{"learn":[0.3795305709],"iteration":68,"passed_time":0.2896724486,"remaining_time":0.1301426943},
{"learn":[0.3774716287],"iteration":69,"passed_time":0.2931797213,"remaining_time":0.125648452},
{"learn":[0.3757557948],"iteration":70,"passed_time":0.2967573992,"remaining_time":0.1212107687},
{"learn":[0.3737958595],"iteration":71,"passed_time":0.3008932806,"remaining_time":0.1170140536},
{"learn":[0.3709682539],"iteration":72,"passed_time":0.3047667481,"remaining_time":0.1127219479},
{"learn":[0.3698490549],"iteration":73,"passed_time":0.3081626103,"remaining_time":0.1082733496},
{"learn":[0.3672435943],"iteration":74,"passed_time":0.3118949663,"remaining_time":0.1039649888},
{"learn":[0.3664775939],"iteration":75,"passed_time":0.3154723907,"remaining_time":0.09962286021},
{"learn":[0.3635119074],"iteration":76,"passed_time":0.3191932645,"remaining_time":0.09534344265},
{"learn":[0.3624823224],"iteration":77,"passed_time":0.3230477876,"remaining_time":0.09111604264},
{"learn":[0.359834243],"iteration":78,"passed_time":0.3266315637,"remaining_time":0.08682611186},
{"learn":[0.3585926304],"iteration":79,"passed_time":0.3301047893,"remaining_time":0.08252619732},
{"learn":[0.3566205723],"iteration":80,"passed_time":0.3335266465,"remaining_time":0.07823464548},
{"learn":[0.3549194757],"iteration":81,"passed_time":0.3370791024,"remaining_time":0.07399297369},
{"learn":[0.3534145052],"iteration":82,"passed_time":0.3404301503,"remaining_time":0.06972665729},
{"learn":[0.3520866845],"iteration":83,"passed_time":0.3439462876,"remaining_time":0.06551357859},
{"learn":[0.3506581117],"iteration":84,"passed_time":0.3476802598,"remaining_time":0.06135533996},
{"learn":[0.3470974583],"iteration":85,"passed_time":0.3516809789,"remaining_time":0.05725039192},
{"learn":[0.3453348242],"iteration":86,"passed_time":0.3552225529,"remaining_time":0.05307923205},
{"learn":[0.3434406268],"iteration":87,"passed_time":0.3588992747,"remaining_time":0.04894081019},
{"learn":[0.3419842448],"iteration":88,"passed_time":0.3624233586,"remaining_time":0.04479389825},
{"learn":[0.3403832174],"iteration":89,"passed_time":0.3658596959,"remaining_time":0.04065107732},
{"learn":[0.3392723051],"iteration":90,"passed_time":0.3691572604,"remaining_time":0.03651005872},
{"learn":[0.3383078703],"iteration":91,"passed_time":0.3725405688,"remaining_time":0.03239483207},
{"learn":[0.3360650035],"iteration":92,"passed_time":0.3761578397,"remaining_time":0.02831295568},
{"learn":[0.3332071138],"iteration":93,"passed_time":0.3796629485,"remaining_time":0.02423380523},
{"learn":[0.3321035348],"iteration":94,"passed_time":0.3831567417,"remaining_time":0.0201661443},
{"learn":[0.3294662596],"iteration":95,"passed_time":0.3865273703,"remaining_time":0.0161053071},
{"learn":[0.3278602225],"iteration":96,"passed_time":0.3899863401,"remaining_time":0.0120614332},
{"learn":[0.3270715433],"iteration":97,"passed_time":0.3938451262,"remaining_time":0.008037655638},
{"learn":[0.3253893292],"iteration":98,"passed_time":0.3973798353,"remaining_time":0.00401393773},
{"learn":[0.3224510494],"iteration":99,"passed_time":0.4009622808,"remaining_time":0}
]}